tests/__init__.py
tests/test_basic.py
tests/test_models.py
tests/integrations/__init__.py
tests/parsing/__init__.py
tests/parsing/test_convenience.py
tests/parsing/test_parser.py
tests/parsing/resources/xml_1_test.xml
tests/parsing/resources/xml_2_test.xml
typecraft_python/__init__.py
typecraft_python/models.py
typecraft_python/util.py
typecraft_python/cli/__init__.py
typecraft_python/cli/main.py
typecraft_python/cli/util.py
typecraft_python/core/__init__.py
typecraft_python/core/exceptions.py
typecraft_python/core/globals.py
typecraft_python/core/interfaces.py
typecraft_python/core/models.py
typecraft_python/integrations/__init__.py
typecraft_python/integrations/nltk/__init__.py
typecraft_python/integrations/nltk/lemmatization.py
typecraft_python/integrations/nltk/ne.py
typecraft_python/integrations/nltk/tagger.py
typecraft_python/integrations/nltk/tests.py
typecraft_python/integrations/nltk/tokenization.py
typecraft_python/integrations/nltk/util.py
typecraft_python/integrations/obt/__init__.py
typecraft_python/integrations/obt/tagger.py
typecraft_python/integrations/obt/tests.py
typecraft_python/integrations/treetagger/__init__.py
typecraft_python/integrations/treetagger/tagger.py
typecraft_python/integrations/treetagger/tests.py
typecraft_python/integrations/treetagger/util.py
typecraft_python/parsing/__init__.py
typecraft_python/parsing/convenience.py
typecraft_python/parsing/mappings.py
typecraft_python/parsing/parallell.py
typecraft_python/parsing/parser.py
typecraft_python/parsing/tests.py
typecraft_python-0.11.0.dist-info/METADATA
typecraft_python-0.11.0.dist-info/RECORD
typecraft_python-0.11.0.dist-info/WHEEL
typecraft_python-0.11.0.dist-info/entry_points.txt
typecraft_python-0.11.0.dist-info/top_level.txt
