Metadata-Version: 2.1
Name: typecraft-python
Version: 0.11.0
Summary: Lightweight implementation of the Typecraft XML format in python.
Home-page: https://github.com/Typecraft/typecraft_python
Author: Tormod Haugland
Author-email: tormod.haugland@gmail.com
License: MIT license
Keywords: typecraft_python
Platform: UNKNOWN
Classifier: Development Status :: 3 - Alpha
Classifier: Intended Audience :: Developers
Classifier: License :: OSI Approved :: MIT License
Classifier: Natural Language :: English
Classifier: Programming Language :: Python :: 2
Classifier: Programming Language :: Python :: 2.7
Classifier: Programming Language :: Python :: 3
Classifier: Programming Language :: Python :: 3.4
Classifier: Programming Language :: Python :: 3.6
Requires-Dist: PYyaml
Requires-Dist: enum34
Requires-Dist: numpy
Requires-Dist: treetaggerwrapper
Requires-Dist: click
Requires-Dist: six
